[
  {
    "objectId": 1008,
    "durations": [],
    "touches": []
  },
  {
    "objectId": 1009,
    "durations": [],
    "touches": []
  },
  {
    "objectId": 1001,
    "durations": [],
    "touches": []
  },
  {
    "objectId": 1002,
    "durations": [],
    "touches": []
  },
  {
    "objectId": 1005,
    "durations": [],
    "touches": []
  },
  {
    "objectId": 1010,
    "durations": [],
    "touches": []
  },
  {
    "objectId": 1013,
    "durations": [],
    "touches": []
  },
  {
    "objectId": 1006,
    "durations": [],
    "touches": []
  },
  {
    "objectId": 1012,
    "durations": [],
    "touches": []
  },
  {
    "objectId": 1004,
    "durations": [],
    "touches": []
  },
  {
    "objectId": 1003,
    "durations": [],
    "touches": []
  },
  {
    "objectId": 1014,
    "durations": [],
    "touches": []
  },
  {
    "objectId": 1000,
    "durations": [],
    "touches": []
  }
]